swan/__init__.py
swan/automatic_mapping.py
swan/export.py
swan/main.py
swan/neo_utils.py
swan/neodata.py
swan/storage.py
swan/version.py
swan/virtual_unit_map.py
swan/app/__init__.py
swan/app/start.py
swan/base/__init__.py
swan/base/project.py
swan/base/storage.py
swan/gui/__init__.py
swan/gui/file_dialog_ui.py
swan/gui/isi_options_ui.py
swan/gui/main_ui.py
swan/gui/palettes.py
swan/gui/parameter_input_dialog_ui.py
swan/gui/plotgrid_ui.py
swan/gui/preferences_dialog_ui.py
swan/gui/rate_profile_options_ui.py
swan/gui/selector_widget_ui.py
swan/gui/virtual_unit_map_view_ui.py
swan/resources/__init__.py
swan/resources/icons.py
swan/views/__init__.py
swan/views/isi_histograms_view.py
swan/views/mean_waveforms_view.py
swan/views/pca_2d_view.py
swan/views/pca_3d_view.py
swan/views/rate_profile_view.py
swan/views/virtual_unit_map_view.py
swan/views/virtual_units_view.py
swan/views/waveforms_3d_view.py
swan/widgets/__init__.py
swan/widgets/file_dialog.py
swan/widgets/gl_view_widget.py
swan/widgets/indicator_cell.py
swan/widgets/matplotlib_widget.py
swan/widgets/mypgwidget.py
swan/widgets/plot_grid.py
swan/widgets/plot_grid_tools.py
swan/widgets/plot_widget.py
swan/widgets/preferences_dialog.py
swan/widgets/selector_widget.py
swan/widgets/view_toolbar.py
tests/__init__.py
tests/test_export.py
tests/test_main.py
tests/test_virtualunitmap.py
python_swan-0.1.0.dist-info/LICENSE.txt
python_swan-0.1.0.dist-info/METADATA
python_swan-0.1.0.dist-info/WHEEL
python_swan-0.1.0.dist-info/dependency_links.txt
python_swan-0.1.0.dist-info/entry_points.txt
python_swan-0.1.0.dist-info/top_level.txt
python_swan-0.1.0.dist-info/RECORD
