Metadata-Version: 2.1
Name: python-swan
Version: 0.1.0
Summary: Python based tool for tracking single units from spike sorted data across several electrophysiological recording sessions.
Home-page: https://github.com/INM-6/swan
Author: SWAN authors and contributors
Author-email: shashwat.sridhar.95@gmail.com
License: BSD-3-Clause
Download-URL: https://github.com/INM-6/swan
Platform: UNKNOWN
Classifier: Development Status :: 3 - Alpha
Classifier: Intended Audience :: Science/Research
Classifier: License :: OSI Approved :: BSD License
Classifier: Natural Language :: English
Classifier: Operating System :: OS Independent
Classifier: Programming Language :: Python :: 3 :: Only
Classifier: Topic :: Scientific/Engineering
License-File: LICENSE.txt
Requires-Dist: numpy (==1.20.3)
Requires-Dist: quantities (==0.12.4)
Requires-Dist: PyQt5 (==5.15.4)
Requires-Dist: pyqtgraph (==0.11.1)
Requires-Dist: odml (==1.5.1)
Requires-Dist: elephant (==0.8.0)
Requires-Dist: neo (==0.8.0)
Requires-Dist: pyopengl (==3.1.5)
Requires-Dist: matplotlib (==3.4.2)
Requires-Dist: scikit-learn (==0.24.2)
Requires-Dist: psutil (==5.8.0)
Requires-Dist: scipy (==1.6.3)
Requires-Dist: pandas (==1.2.4)
Requires-Dist: colorcet (==2.0.6)
